msadapter/__init__.py
msadapter/package_info.py
msadapter/utils.py
msadapter/pytorch/__init__.py
msadapter/pytorch/_register_numpy_primitive.py
msadapter/pytorch/_six.py
msadapter/pytorch/_utils.py
msadapter/pytorch/conflict_functional.py
msadapter/pytorch/functional.py
msadapter/pytorch/hub.py
msadapter/pytorch/random.py
msadapter/pytorch/serialization.py
msadapter/pytorch/storage.py
msadapter/pytorch/tensor.py
msadapter/pytorch/_ref/__init__.py
msadapter/pytorch/_register/__init__.py
msadapter/pytorch/_register/getitem_impl.py
msadapter/pytorch/_register/register_multitype_ops.py
msadapter/pytorch/_register/register_standard_method.py
msadapter/pytorch/_register/register_utils.py
msadapter/pytorch/amp/__init__.py
msadapter/pytorch/autograd/__init__.py
msadapter/pytorch/autograd/function.py
msadapter/pytorch/autograd/variable.py
msadapter/pytorch/common/__init__.py
msadapter/pytorch/common/_inner.py
msadapter/pytorch/common/device.py
msadapter/pytorch/common/dtype.py
msadapter/pytorch/cuda/__init__.py
msadapter/pytorch/fft/__init__.py
msadapter/pytorch/fft/fft.py
msadapter/pytorch/linalg/__init__.py
msadapter/pytorch/linalg/linalg.py
msadapter/pytorch/nn/__init__.py
msadapter/pytorch/nn/functional.py
msadapter/pytorch/nn/init.py
msadapter/pytorch/nn/parameter.py
msadapter/pytorch/nn/modules/__init__.py
msadapter/pytorch/nn/modules/activation.py
msadapter/pytorch/nn/modules/adaptive.py
msadapter/pytorch/nn/modules/batchnorm.py
msadapter/pytorch/nn/modules/channelshuffle.py
msadapter/pytorch/nn/modules/container.py
msadapter/pytorch/nn/modules/conv.py
msadapter/pytorch/nn/modules/distance.py
msadapter/pytorch/nn/modules/dropout.py
msadapter/pytorch/nn/modules/flatten.py
msadapter/pytorch/nn/modules/fold.py
msadapter/pytorch/nn/modules/linear.py
msadapter/pytorch/nn/modules/loss.py
msadapter/pytorch/nn/modules/module.py
msadapter/pytorch/nn/modules/normalization.py
msadapter/pytorch/nn/modules/padding.py
msadapter/pytorch/nn/modules/pixel_shuffle.py
msadapter-0.1.0.dist-info/LICENSE
msadapter-0.1.0.dist-info/METADATA
msadapter-0.1.0.dist-info/WHEEL
msadapter-0.1.0.dist-info/top_level.txt
msadapter-0.1.0.dist-info/RECORD
